.gitignore
.travis.yml
LICENSE-GPLv3
LICENSE-MPL
README.rst
setup.cfg
setup.py
tox.ini
docs/about.rst
docs/api.rst
docs/basics.rst
docs/conf.py
docs/index.rst
src/deprecate/__init__.py
src/deprecate.egg-info/PKG-INFO
src/deprecate.egg-info/SOURCES.txt
src/deprecate.egg-info/dependency_links.txt
src/deprecate.egg-info/top_level.txt
testing/test_deprecate.py