Metadata-Version: 1.1
Name: deprecate
Version: 1.0.5
Summary: Python deprecating solution.
Home-page: https://github.com/mfalesni/python-deprecate
Author: Milan Falešník
Author-email: milan@falesnik.net
License: GPLv3,MPLv2
Keywords: deprecate
Platform: UNKNOWN
Classifier: Topic :: Utilities
Classifier: License :: OSI Approved :: GNU General Public License v3 (GPLv3)
Classifier: License :: OSI Approved :: Mozilla Public License 2.0 (MPL 2.0)
Classifier: Topic :: Software Development :: Libraries :: Python Modules
Classifier: Programming Language :: Python :: 2.7
Classifier: Programming Language :: Python :: 3.3
Classifier: Programming Language :: Python :: 3.4
Classifier: Programming Language :: Python :: 3.5
Classifier: Intended Audience :: Developers
Classifier: Development Status :: 4 - Beta
